geoweather/__init__.py
geoweather-0.1.dist-info/DESCRIPTION.rst
geoweather-0.1.dist-info/METADATA
geoweather-0.1.dist-info/RECORD
geoweather-0.1.dist-info/WHEEL
geoweather-0.1.dist-info/metadata.json
geoweather-0.1.dist-info/top_level.txt
